acct_backends/conf.py
acct_backends/version.py
acct_backends/acct/1password.py
acct_backends/acct/bitwarden.py
acct_backends/acct/keybase.py
acct_backends/acct/keychain.py
acct_backends/acct/lastpass.py
acct_backends/acct/secretstorage.py
acct_backends/acct/vault.py
acct_backends/acct/wallet.py
acct_backends-0.2.dist-info/METADATA
acct_backends-0.2.dist-info/WHEEL
acct_backends-0.2.dist-info/top_level.txt
acct_backends-0.2.dist-info/RECORD
