Metadata-Version: 2.1
Name: acct-backends
Version: 0.2
Summary: Backends for acct authentication in idem/POP
Home-page: https://gitlab.com/Akm0d/acct-backends
Author: Tyler Johnson
Author-email: tjohnson@saltstack.com
License: UNKNOWN
Platform: UNKNOWN
Classifier: Operating System :: OS Independent
Classifier: Programming Language :: Python
Classifier: Programming Language :: Python :: 3.6
Classifier: Programming Language :: Python :: 3.7
Classifier: Programming Language :: Python :: 3.8
Classifier: Development Status :: 5 - Production/Stable
Requires-Python: >=3.6
Requires-Dist: pop
Requires-Dist: lastpass-python (>=0.3.1)
Requires-Dist: secretstorage (==3.1.2)
